compare_locales/__init__.py
compare_locales/commands.py
compare_locales/keyedtuple.py
compare_locales/merge.py
compare_locales/mozpath.py
compare_locales/plurals.py
compare_locales/serializer.py
compare_locales/util.py
compare_locales/checks/__init__.py
compare_locales/checks/android.py
compare_locales/checks/base.py
compare_locales/checks/dtd.py
compare_locales/checks/fluent.py
compare_locales/checks/properties.py
compare_locales/compare/__init__.py
compare_locales/compare/content.py
compare_locales/compare/observer.py
compare_locales/compare/utils.py
compare_locales/lint/__init__.py
compare_locales/lint/cli.py
compare_locales/lint/linter.py
compare_locales/lint/util.py
compare_locales/parser/__init__.py
compare_locales/parser/android.py
compare_locales/parser/base.py
compare_locales/parser/defines.py
compare_locales/parser/dtd.py
compare_locales/parser/fluent.py
compare_locales/parser/ini.py
compare_locales/parser/po.py
compare_locales/parser/properties.py
compare_locales/paths/__init__.py
compare_locales/paths/configparser.py
compare_locales/paths/files.py
compare_locales/paths/ini.py
compare_locales/paths/matcher.py
compare_locales/paths/project.py
compare_locales-9.0.3.dist-info/LICENSE.md
compare_locales-9.0.3.dist-info/METADATA
compare_locales-9.0.3.dist-info/WHEEL
compare_locales-9.0.3.dist-info/entry_points.txt
compare_locales-9.0.3.dist-info/top_level.txt
compare_locales-9.0.3.dist-info/RECORD
