Metadata-Version: 2.1
Name: compare-locales
Version: 9.0.3
Summary: Lint Mozilla localizations
Author: Axel Hecht
Author-email: Mozilla <l10n-drivers@mozilla.org>, Eemeli Aro <eemeli@mozilla.com>
License: MPL-2.0
Project-URL: repository, https://github.com/mozilla/compare-locales
Platform: any
Classifier: Development Status :: 5 - Production/Stable
Classifier: Intended Audience :: Developers
Classifier: License :: OSI Approved :: Mozilla Public License 2.0 (MPL 2.0)
Classifier: Operating System :: OS Independent
Classifier: Programming Language :: Python
Classifier: Programming Language :: Python :: 3
Classifier: Programming Language :: Python :: 3.7
Classifier: Programming Language :: Python :: 3.8
Classifier: Programming Language :: Python :: 3.9
Classifier: Programming Language :: Python :: 3.10
Classifier: Topic :: Software Development :: Libraries :: Python Modules
Classifier: Topic :: Software Development :: Localization
Classifier: Topic :: Software Development :: Testing
Requires-Python: <4,>=3.7
License-File: LICENSE.md
Requires-Dist: fluent.syntax <0.20,>=0.18.0
Requires-Dist: six
Requires-Dist: toml
